pose_tracking_3d/__init__.py
pose_tracking_3d/core.py
wf_pose_tracking_3d-0.1.0.dist-info/LICENSE
wf_pose_tracking_3d-0.1.0.dist-info/METADATA
wf_pose_tracking_3d-0.1.0.dist-info/WHEEL
wf_pose_tracking_3d-0.1.0.dist-info/top_level.txt
wf_pose_tracking_3d-0.1.0.dist-info/RECORD
