Metadata-Version: 2.1
Name: wf-pose-tracking-3d
Version: 0.1.0
Summary: Classes and methods for performing 3D pose tracking from 2D poses
Home-page: https://github.com/WildflowerSchools/wf-pose-tracking-3d
Author: Theodore Quinn
Author-email: ted.quinn@wildflowerschools.org
License: UNKNOWN
Keywords: cv
Platform: UNKNOWN
Classifier: Intended Audience :: Developers
Classifier: License :: OSI Approved :: MIT License
Classifier: Operating System :: OS Independent
Classifier: Programming Language :: Python
Requires-Dist: wf-cv-utils (>=0.1.0)
Requires-Dist: wf-cv-datetime-utils (>=0.1.0)
Requires-Dist: wf-smc-kalman (>=0.1.0)
Requires-Dist: numpy (>=1.14)
Requires-Dist: scipy (>=1.1)
Requires-Dist: pandas (>=0.23)
Requires-Dist: matplotlib (>=2.2)
Requires-Dist: networkx (>=2.1)
Requires-Dist: boto3 (>=1.7)
